my_aws_helpers/api.py
my_aws_helpers/cognito.py
my_aws_helpers/dynamo.py
my_aws_helpers/errors.py
my_aws_helpers/logging.py
my_aws_helpers/s3.py
my_aws_helpers/sfn.py
my_aws_helpers-1.7.0.dist-info/METADATA
my_aws_helpers-1.7.0.dist-info/WHEEL
my_aws_helpers-1.7.0.dist-info/top_level.txt
my_aws_helpers-1.7.0.dist-info/zip-safe
my_aws_helpers-1.7.0.dist-info/RECORD
