Metadata-Version: 2.1
Name: my_aws_helpers
Version: 1.7.0
Summary: AWS Helpers
Home-page: https://github.com/JarrodMccarthy/aws_helpers.git
Author: Jarrod McCarthy
Platform: any
Classifier: License :: Other/Proprietary License
Classifier: Programming Language :: Python
Classifier: Programming Language :: Python :: 3.8
Classifier: Programming Language :: Python :: 3.9
Classifier: Programming Language :: Python :: 3.10
Requires-Dist: boto3==1.34.36
